src/__init__.py
src/app.py
src/header.html
src/version.py
src/__pycache__/__init__.cpython-310.pyc
src/__pycache__/version.cpython-310.pyc
src/examples/2list_1table.pdf
src/examples/3list_1table.pdf
src/examples/academic_paper_formula.pdf
src/examples/academic_paper_img_formula.pdf
src/examples/academic_paper_list.pdf
src/examples/complex_layout.pdf
src/examples/complex_layout_para_split_list.pdf
src/examples/garbled_formula.pdf
src/examples/magazine_complex_layout_images_list.pdf
src/examples/scanned.pdf
mineru_app-0.0.6.dist-info/METADATA
mineru_app-0.0.6.dist-info/WHEEL
mineru_app-0.0.6.dist-info/entry_points.txt
mineru_app-0.0.6.dist-info/top_level.txt
mineru_app-0.0.6.dist-info/RECORD
