Metadata-Version: 2.1
Name: mineru-app
Version: 0.0.6
Summary: A PDF processing and conversion tool
Home-page: https://github.com/opendatalab/MinerU-App
Author: Opendatalab
Classifier: Programming Language :: Python :: 3
Classifier: License :: OSI Approved :: MIT License
Classifier: Operating System :: OS Independent
Requires-Python: >=3.10
Requires-Dist: requests
Requires-Dist: python-dotenv
Requires-Dist: PyMuPDF<=1.24.14,>=1.24.9
Requires-Dist: gradio==5.6.0
Requires-Dist: gradio-client==1.4.3
Requires-Dist: gradio-pdf==0.0.19
